auth/JWTBearer.py
auth/__init__.py
auth/auth.py
auth/db_connection.py
auth/models.py
auth/permission.py
auth/router.py
auth/routes/__init__.py
auth/routes/group_user.py
auth/routes/groups.py
auth/routes/roles.py
auth/routes/roles_entities.py
auth/routes/user_handlers.py
auth/routes/users.py
auth/schemas/__init__.py
auth/schemas/models.py
auth/utils/__init__.py
auth/utils/event_crud.py
auth/utils/event_user_crud.py
auth/utils/group_crud.py
auth/utils/group_user_crud.py
auth/utils/permission_crud.py
auth/utils/permission_entitites_crud.py
auth/utils/role_crud.py
auth/utils/user_crud.py
ofry_fasatpi_auth_cognito-0.0.4.dist-info/METADATA
ofry_fasatpi_auth_cognito-0.0.4.dist-info/WHEEL
ofry_fasatpi_auth_cognito-0.0.4.dist-info/top_level.txt
ofry_fasatpi_auth_cognito-0.0.4.dist-info/RECORD
