Metadata-Version: 2.1
Name: ofry-fasatpi-auth-cognito
Version: 0.0.4
Summary: User management authentiation
Author: Ofry Makdasy
Author-email: ofry.makdsy@tech-19.com
Keywords: python,first package,fastapi,cognito,jwt
Classifier: Development Status :: 3 - Alpha
Classifier: Intended Audience :: Education
Classifier: Programming Language :: Python :: 2
Classifier: Programming Language :: Python :: 3
Classifier: Operating System :: MacOS :: MacOS X
Classifier: Operating System :: Microsoft :: Windows
Requires-Dist: fastapi
Requires-Dist: python-dotenv (==0.21.0)
Requires-Dist: python-jose (==3.3.0)
Requires-Dist: requests (==2.28.2)
Requires-Dist: SQLAlchemy (==1.4.46)
